{
    "Animations": [{
                   "MovingAnimations": [{
                                        "id": "superAceFire",
                                        "dx": 0,
                                        "dy": -4,
                                        "delay": 10,
                                        "continuous": true
                                        }, {
                                        "id": "straightEnemyAttack",
                                        "dx": 0,
                                        "dy": 2,
                                        "delay": 10,
                                        "continuous": true
                                        }]
                   }, {
                   "MovingPathAnimations": [{
                                            "id": "superAceAnimationUp",
                                            "paths": [{
                                                      "dx": 0,
                                                      "dy": -5,
                                                      "frameNo": 0,
                                                      "visibility": true,
                                                      "delay": 10
                                                      }, {
                                                      "dx": 0,
                                                      "dy": -5,
                                                      "frameNo": 1,
                                                      "visibility": true,
                                                      "delay": 10
                                                      }]
                                            },{
                                            "id": "explosion",
                                            "paths": [{
                                                      "dx": 0,
                                                      "dy": 2,
                                                      "visibility": true,
                                                      "frameNo": 0,
                                                      "delay": 90
                                                      }, {
                                                      "dx": 0,
                                                      "dy": 2,
                                                      "visibility": true,
                                                      "frameNo": 1,
                                                      "delay": 90
                                                      }, {
                                                      "dx": 0,
                                                      "dy": 2,
                                                      "frameNo": 2,
                                                      "visibility": true,
                                                      "delay": 90
                                                      }, {
                                                      "dx": 0,
                                                      "dy": 2,
                                                      "frameNo": 3,
                                                      "visibility": true,
                                                      "delay": 90
                                                      }, {
                                                      "dx": 0,
                                                      "dy": 2,
                                                      "frameNo": 4,
                                                      "visibility": true,
                                                      "delay": 90
                                                      }, {
                                                      "dx": 0,
                                                      "dy": 2,
                                                      "frameNo": 5,
                                                      "visibility": true,
                                                      "delay": 90
                                                      },{
                                                      "dx": 0,
                                                      "dy": 2,
                                                      "frameNo": 5,
                                                      "visibility": false,
                                                      "delay": 90
                                                      }]
                                            },{
                                            "id": "explosion",
                                            "paths": [{
                                                      "dx": 0,
                                                      "dy": 2,
                                                      "visibility": true,
                                                      "frameNo": 0,
                                                      "delay": 90
                                                      }, {
                                                      "dx": 0,
                                                      "dy": 2,
                                                      "visibility": true,
                                                      "frameNo": 1,
                                                      "delay": 90
                                                      }, {
                                                      "dx": 0,
                                                      "dy": 2,
                                                      "frameNo": 2,
                                                      "visibility": true,
                                                      "delay": 90
                                                      }, {
                                                      "dx": 0,
                                                      "dy": 2,
                                                      "frameNo": 3,
                                                      "visibility": true,
                                                      "delay": 90
                                                      }, {
                                                      "dx": 0,
                                                      "dy": 2,
                                                      "frameNo": 4,
                                                      "visibility": true,
                                                      "delay": 90
                                                      }, {
                                                      "dx": 0,
                                                      "dy": 2,
                                                      "frameNo": 5,
                                                      "visibility": true,
                                                      "delay": 90
                                                      },{
                                                      "dx": 0,
                                                      "dy": 2,
                                                      "frameNo": 5,
                                                      "visibility": false,
                                                      "delay": 90
                                                      }]
                                            }, {
                                            "id": "circle_250_250_30",
                                            "paths": [{
                                                      "dx": 10,
                                                      "dy": 10,
                                                      "frameNo": 0,
                                                      "visibility": true,
                                                      "delay": 150
                                                      },{
                                                      "dx": 10,
                                                      "dy": 10,
                                                      "frameNo": 0,
                                                      "visibility": true,
                                                      "delay": 150
                                                      },{
                                                      "dx": 10,
                                                      "dy": 10,
                                                      "frameNo": 0,
                                                      "visibility": true,
                                                      "delay": 150
                                                      },{
                                                      "dx": 10,
                                                      "dy": 10,
                                                      "frameNo": 0,
                                                      "visibility": true,
                                                      "delay": 150
                                                      },{
                                                      "dx": 10,
                                                      "dy": 10,
                                                      "frameNo": 0,
                                                      "visibility": true,
                                                      "delay": 150
                                                      },{
                                                      "dx": 10,
                                                      "dy": 10,
                                                      "frameNo": 0,
                                                      "visibility": true,
                                                      "delay": 150
                                                      },{
                                                      "dx": 10,
                                                      "dy": 10,
                                                      "frameNo": 0,
                                                      "visibility": true,
                                                      "delay": 150
                                                      },{
                                                      "dx": 10,
                                                      "dy": 10,
                                                      "frameNo": 0,
                                                      "visibility": true,
                                                      "delay": 150
                                                      },{
                                                      "dx": 10,
                                                      "dy": 10,
                                                      "frameNo": 0,
                                                      "visibility": true,
                                                      "delay": 150
                                                      },{
                                                      "dx": 10,
                                                      "dy": 10,
                                                      "frameNo": 0,
                                                      "visibility": true,
                                                      "delay": 150
                                                      },{
                                                      "dx": 10,
                                                      "dy": 10,
                                                      "frameNo": 0,
                                                      "visibility": true,
                                                      "delay": 150
                                                      },{
                                                      "dx": 10,
                                                      "dy": 10,
                                                      "frameNo": 0,
                                                      "visibility": true,
                                                      "delay": 150
                                                      },{
                                                      "dx": 10,
                                                      "dy": 10,
                                                      "frameNo": 0,
                                                      "visibility": true,
                                                      "delay": 150
                                                      },{
                                                      "dx": 10,
                                                      "dy": 10,
                                                      "frameNo": 0,
                                                      "visibility": true,
                                                      "delay": 150
                                                      },{
                                                      "dx": 10,
                                                      "dy": 10,
                                                      "frameNo": 0,
                                                      "visibility": true,
                                                      "delay": 150
                                                      },{
                                                      "dx": -3,
                                                      "dy": 12,
                                                      "frameNo": 15,
                                                      "visibility": true,
                                                      "delay": 150
                                                      }, {
                                                      "dx": -7,
                                                      "dy": 10,
                                                      "frameNo": 14,
                                                      "visibility": true,
                                                      "delay": 150
                                                      },{
                                                      "dx": -11,
                                                      "dy": 6,
                                                      "frameNo": 13,
                                                      "visibility": true,
                                                      "delay": 150
                                                      }, {
                                                      "dx": -12,
                                                      "dy": 1,
                                                      "frameNo": 12,
                                                      "visibility": true,
                                                      "delay": 150
                                                      },{
                                                      "dx": -12,
                                                      "dy": -4,
                                                      "frameNo": 11,
                                                      "visibility": true,
                                                      "delay": 150
                                                      }, {
                                                      "dx": -9,
                                                      "dy": -8,
                                                      "frameNo": 10,
                                                      "visibility": true,
                                                      "delay": 150
                                                      },{
                                                      "dx": -5,
                                                      "dy": -11,
                                                      "frameNo": 9,
                                                      "visibility": true,
                                                      "delay": 150
                                                      }, {
                                                      "dx": 0,
                                                      "dy": -12,
                                                      "frameNo": 8,
                                                      "visibility": true,
                                                      "delay": 150
                                                      },{
                                                      "dx": 5,
                                                      "dy": -11,
                                                      "frameNo": 7,
                                                      "visibility": true,
                                                      "delay": 150
                                                      }, {
                                                      "dx": 9,
                                                      "dy": -8,
                                                      "frameNo": 6,
                                                      "visibility": true,
                                                      "delay": 150
                                                      },{
                                                      "dx": 12,
                                                      "dy": -4,
                                                      "frameNo": 5,
                                                      "visibility": true,
                                                      "delay": 150
                                                      }, {
                                                      "dx": 12,
                                                      "dy": 1,
                                                      "frameNo": 4,
                                                      "visibility": true,
                                                      "delay": 150
                                                      },{
                                                      "dx": 11,
                                                      "dy": 6,
                                                      "frameNo": 3,
                                                      "visibility": true,
                                                      "delay": 150
                                                      }, {
                                                      "dx": 7,
                                                      "dy": 10,
                                                      "frameNo": 2,
                                                      "visibility": true,
                                                      "delay": 150
                                                      },{
                                                      "dx": 20,
                                                      "dy": 5,
                                                      "visibility": true,
                                                      "frameNo": 1,
                                                      "delay": 150
                                                      }, {
                                                      "dx": 20,
                                                      "dy": 5,
                                                      "frameNo": 0,
                                                      "visibility": true,
                                                      "delay": 150
                                                      }, {
                                                      "dx": 20,
                                                      "dy": 5,
                                                      "frameNo": 0,
                                                      "visibility": true,
                                                      "delay": 150
                                                      }]
                                            }, {
                                            "id": "superAceAnimationDown",
                                            "paths": [{
                                                      "dx": 0,
                                                      "dy": 5,
                                                      "visibility": true,
                                                      "frameNo": 0,
                                                      "delay": 10
                                                      }, {
                                                      "dx": 0,
                                                      "dy": 5,
                                                      "frameNo": 0,
                                                      "visibility": true,
                                                      "delay": 10
                                                      }]
                                            }, {
                                            "id": "superAceAnimationManeuver",
                                            "paths": [{
                                                      "dx": 0,
                                                      "dy": -1,
                                                      "frameNo": 0,
                                                      "visibility": true,
                                                      "delay": 90
                                                      }, {
                                                      "dx": 0,
                                                      "dy": -1,
                                                      "frameNo": 10,
                                                      "visibility": true,
                                                      "delay": 90
                                                      },{
                                                      "dx": 0,
                                                      "dy": -1,
                                                      "frameNo": 11,
                                                      "visibility": true,
                                                      "delay": 90
                                                      },{
                                                      "dx": 0,
                                                      "dy": -1,
                                                      "frameNo": 12,
                                                      "visibility": true,
                                                      "delay": 90
                                                      },{
                                                      "dx": 0,
                                                      "dy": -1,
                                                      "visibility": true,
                                                      "frameNo": 13,
                                                      "delay": 90
                                                      },{
                                                      "dx": 0,
                                                      "dy": -1,
                                                      "visibility": true,
                                                      "frameNo": 14,
                                                      "delay": 90
                                                      },{
                                                      "dx": 0,
                                                      "dy": -1,
                                                      "frameNo": 15,
                                                      "visibility": true,
                                                      "delay": 90
                                                      },{
                                                      "dx": 0,
                                                      "dy": -1,
                                                      "frameNo": 16,
                                                      "visibility": true,
                                                      "delay": 90
                                                      },{
                                                      "dx": 0,
                                                      "dy": -1,
                                                      "frameNo": 17,
                                                      "visibility": true,
                                                      "delay": 90
                                                      },{
                                                      "dx": 0,
                                                      "dy": 1,
                                                      "frameNo": 18,
                                                      "visibility": true,
                                                      "delay": 90
                                                      },{
                                                      "dx": 0,
                                                      "dy": 1,
                                                      "frameNo": 19,
                                                      "visibility": true,
                                                      "delay": 90
                                                      },{
                                                      "dx": 0,
                                                      "dy": 1,
                                                      "frameNo": 20,
                                                      "visibility": true,
                                                      "delay": 90
                                                      },{
                                                      "dx": 0,
                                                      "dy": 1,
                                                      "frameNo": 21,
                                                      "visibility": true,
                                                      "delay": 90
                                                      },{
                                                      "dx": 0,
                                                      "dy": 1,
                                                      "frameNo": 22,
                                                      "visibility": true,
                                                      "delay": 90
                                                      },{
                                                      "dx": 0,
                                                      "dy": 1,
                                                      "frameNo": 23,
                                                      "visibility": true,
                                                      "delay": 90
                                                      },{
                                                      "dx": 0,
                                                      "dy": -1,
                                                      "frameNo": 0,
                                                      "visibility": true,
                                                      "delay": 0
                                                      }]
                                            }, {
                                            "id": "superAceAnimationLeft",
                                            "paths": [{
                                                      "dx": -5,
                                                      "dy": 0,
                                                      "frameNo": 0,
                                                      "visibility": true,
                                                      "delay": 10
                                                      }, {
                                                      "dx": -5,
                                                      "dy": 0,
                                                      "frameNo": 1,
                                                      "visibility": true,
                                                      "delay": 10
                                                      }]
                                            },{
                                            "id": "superAceStartingAnimation",
                                            "paths": [{
                                                      "dx": -5,
                                                      "dy": 0,
                                                      "frameNo": 13,
                                                      "visibility": true,
                                                      "delay": 90
                                                      },{
                                                      "dx": -5,
                                                      "dy": 0,
                                                      "frameNo": 15,
                                                      "visibility": true,
                                                      "delay": 90
                                                      },{
                                                      "dx": -5,
                                                      "visibility": true,
                                                      "dy": 0,
                                                      "frameNo": 15,
                                                      "delay": 10
                                                      },{
                                                      "dx": 5,
                                                      "dy": 0,
                                                      "visibility": true,
                                                      "frameNo": 0,
                                                      "delay": 10
                                                      },{
                                                      "dx": 5,
                                                      "dy": 0,
                                                      "frameNo": 0,
                                                      "visibility": true,
                                                      "delay": 10
                                                      }]
                                            }, {
                                            "id": "superAceAnimationRight",
                                            "paths": [{
                                                      "dx": 5,
                                                      "dy": 0,
                                                      "frameNo": 0,
                                                      "visibility": true,
                                                      "delay": 10
                                                      }, {
                                                      "dx": 5,
                                                      "dy": 0,
                                                      "frameNo": 0,
                                                      "visibility": true,
                                                      "delay": 10
                                                      }]
                                            }]
                   }]
}